openphonemizer/__init__.py
openphonemizer-0.1.2.dist-info/LICENSE
openphonemizer-0.1.2.dist-info/METADATA
openphonemizer-0.1.2.dist-info/WHEEL
openphonemizer-0.1.2.dist-info/top_level.txt
openphonemizer-0.1.2.dist-info/RECORD
