Metadata-Version: 2.1
Name: openphonemizer
Version: 0.1.2
Summary: Permissively licensed, open sourced, local IPA Phonemizer (G2P) powered by deep learning.
Home-page: https://github.com/NeuralVox/OpenPhonemizer
Author: mrfakename
Author-email: me@mrfake.name
License: BSD-3-Clause-Clear
Classifier: License :: OSI Approved :: BSD License
License-File: LICENSE
Requires-Dist: deep-phonemizer
Requires-Dist: cached-path
Requires-Dist: num2words
